{"stats":{"minecraft:crafted":{"minecraft:oak_planks":308,"minecraft:stone_shovel":2,"minecraft:cooked_chicken":7,"minecraft:lightning_rod":17,"minecraft:furnace":10,"minecraft:stone":1,"minecraft:cooked_mutton":10,"minecraft:bow":1,"minecraft:iron_axe":2,"minecraft:stone_pickaxe":6,"minecraft:chest":3,"minecraft:wheat":477,"minecraft:cooked_beef":22,"minecraft:cooked_porkchop":21,"minecraft:crafting_table":2,"minecraft:wooden_pickaxe":1,"minecraft:baked_potato":7,"minecraft:cooked_salmon":11,"minecraft:copper_ingot":53,"minecraft:leather_helmet":1,"minecraft:bucket":1,"minecraft:stone_axe":4,"minecraft:bread":160,"minecraft:air":0,"minecraft:iron_chestplate":1,"minecraft:shield":2,"minecraft:stick":148,"minecraft:iron_ingot":51,"minecraft:leather_chestplate":1,"minecraft:iron_pickaxe":4,"minecraft:wooden_axe":1,"minecraft:iron_shovel":1,"minecraft:white_bed":1,"minecraft:torch":128,"minecraft:shears":1},"minecraft:dropped":{"minecraft:iron_ingot":19,"minecraft:bread":39,"minecraft:wheat_seeds":12,"minecraft:lapis_lazuli":31,"minecraft:glow_ink_sac":1,"minecraft:cooked_porkchop":3,"minecraft:cobblestone":277,"minecraft:wooden_axe":1,"minecraft:iron_axe":1,"minecraft:iron_pickaxe":1,"minecraft:bucket":1,"minecraft:furnace":5,"minecraft:sugar_cane":9,"minecraft:raw_copper":20,"minecraft:rotten_flesh":7,"minecraft:lightning_rod":10,"minecraft:shield":1,"minecraft:gunpowder":1,"minecraft:oak_wood":6,"minecraft:beef":7,"minecraft:wooden_pickaxe":1},"minecraft:killed":{"minecraft:spider":4,"minecraft:skeleton":5,"minecraft:bee":1,"minecraft:chicken":7,"minecraft:drowned":3,"minecraft:pig":8,"minecraft:zombie_villager":1,"minecraft:salmon":14,"minecraft:creeper":6,"minecraft:sheep":6,"minecraft:zombie":20,"minecraft:donkey":1,"minecraft:cow":15},"minecraft:mined":{"minecraft:oak_sapling":2,"minecraft:mossy_cobblestone":53,"minecraft:glow_lichen":1,"minecraft:granite":17,"minecraft:grass_block":231,"minecraft:spawner":1,"minecraft:hay_block":53,"minecraft:smooth_stone":1,"minecraft:furnace":3,"minecraft:iron_ore":51,"minecraft:andesite":1,"minecraft:fletching_table":1,"minecraft:pointed_dripstone":1,"minecraft:oak_stairs":1,"minecraft:stone":892,"minecraft:crafting_table":8,"minecraft:cornflower":1,"minecraft:torch":2,"minecraft:chest":1,"minecraft:lightning_rod":1,"minecraft:tall_grass":4,"minecraft:copper_ore":12,"minecraft:cobblestone":29,"minecraft:lapis_ore":6,"minecraft:oak_planks":1,"minecraft:diorite":14,"minecraft:wall_torch":8,"minecraft:white_terracotta":1,"minecraft:grass":48,"minecraft:oak_log":76,"minecraft:coal_ore":197,"minecraft:gravel":13,"minecraft:dripstone_block":19,"minecraft:dirt":303,"minecraft:oak_leaves":49},"minecraft:picked_up":{"minecraft:wooden_axe":1,"minecraft:crafting_table":9,"minecraft:chicken":7,"minecraft:wooden_pickaxe":1,"minecraft:lead":1,"minecraft:cornflower":1,"minecraft:string":3,"minecraft:raw_copper":29,"minecraft:smooth_stone":1,"minecraft:beef":29,"minecraft:sugar_cane":2,"minecraft:chest":1,"minecraft:egg":1,"minecraft:furnace":8,"minecraft:stick":6,"minecraft:raw_iron":51,"minecraft:torch":15,"minecraft:porkchop":21,"minecraft:lightning_rod":1,"minecraft:pointed_dripstone":9,"minecraft:diorite":11,"minecraft:arrow":8,"minecraft:rotten_flesh":32,"minecraft:hay_block":53,"minecraft:white_terracotta":1,"minecraft:mutton":10,"minecraft:cobblestone":853,"minecraft:white_wool":13,"minecraft:feather":8,"minecraft:glow_ink_sac":1,"minecraft:salmon":11,"minecraft:andesite":1,"minecraft:leather":16,"minecraft:potato":1,"minecraft:oak_log":77,"minecraft:gunpowder":7,"minecraft:cobblestone_wall":52,"minecraft:lapis_lazuli":31,"minecraft:dirt":521,"minecraft:bone":10,"minecraft:wheat_seeds":12,"minecraft:iron_ingot":2,"minecraft:fletching_table":1,"minecraft:dripstone_block":18,"minecraft:gravel":1,"minecraft:sand":5,"minecraft:mossy_cobblestone":53,"minecraft:oak_wood":6,"minecraft:sugar":1,"minecraft:granite":18,"minecraft:bone_meal":1,"minecraft:oak_sapling":6,"minecraft:coal":242},"minecraft:broken":{"minecraft:iron_shovel":1,"minecraft:stone_pickaxe":6,"minecraft:stone_axe":4,"minecraft:iron_pickaxe":2,"minecraft:wooden_axe":1,"minecraft:stone_shovel":2},"minecraft:custom":{"minecraft:interact_with_smithing_table":1,"minecraft:mob_kills":91,"minecraft:interact_with_crafting_table":56,"minecraft:bell_ring":18,"minecraft:leave_game":1,"minecraft:time_since_death":220681,"minecraft:climb_one_cm":1555,"minecraft:sprint_one_cm":286296,"minecraft:walk_one_cm":722285,"minecraft:drop":28,"minecraft:talked_to_villager":48,"minecraft:play_time":220681,"minecraft:sneak_time":2037,"minecraft:walk_under_water_one_cm":15814,"minecraft:jump":1464,"minecraft:interact_with_brewingstand":1,"minecraft:walk_on_water_one_cm":24384,"minecraft:total_world_time":220681,"minecraft:interact_with_furnace":101,"minecraft:sleep_in_bed":4,"minecraft:time_since_rest":19480,"minecraft:damage_taken":1265,"minecraft:damage_dealt":11486,"minecraft:swim_one_cm":1337,"minecraft:fly_one_cm":134876,"minecraft:open_chest":84,"minecraft:crouch_one_cm":8579,"minecraft:fall_one_cm":23603},"minecraft:used":{"minecraft:iron_shovel":254,"minecraft:stone_shovel":264,"minecraft:chest":4,"minecraft:white_terracotta":1,"minecraft:cooked_salmon":2,"minecraft:cooked_chicken":6,"minecraft:torch":90,"minecraft:dirt":145,"minecraft:cobblestone_wall":52,"minecraft:granite":10,"minecraft:wooden_axe":37,"minecraft:iron_axe":24,"minecraft:bow":11,"minecraft:oak_sapling":5,"minecraft:furnace":13,"minecraft:potato":1,"minecraft:cooked_mutton":5,"minecraft:stone_pickaxe":789,"minecraft:wooden_pickaxe":24,"minecraft:fletching_table":1,"minecraft:mossy_cobblestone":26,"minecraft:sand":5,"minecraft:crafting_table":10,"minecraft:white_bed":1,"minecraft:dripstone_block":18,"minecraft:lightning_rod":2,"minecraft:bread":14,"minecraft:iron_pickaxe":521,"minecraft:stone_axe":367,"minecraft:cobblestone":457}},"DataVersion":3117}